helga_team/__init__.py
helga_team/helga_team.py
helga_team-1.0.2.dist-info/DESCRIPTION.rst
helga_team-1.0.2.dist-info/METADATA
helga_team-1.0.2.dist-info/RECORD
helga_team-1.0.2.dist-info/WHEEL
helga_team-1.0.2.dist-info/entry_points.txt
helga_team-1.0.2.dist-info/metadata.json
helga_team-1.0.2.dist-info/top_level.txt
helga_team-1.0.2.dist-info/zip-safe
tests/__init__.py
tests/test_team.py
