Metadata-Version: 2.0
Name: helga-team
Version: 1.0.2
Summary: Team plugin to track candidates and interview process
Home-page: UNKNOWN
Author: Jon Robison
Author-email: narfman0@gmail.com
License: LICENSE
Keywords: irc bot team
Platform: UNKNOWN
Classifier: Development Status :: 4 - Beta
Classifier: Topic :: Communications :: Chat :: Internet Relay Chat
Classifier: License :: OSI Approved :: GNU General Public License v3 (GPLv3)
Classifier: Operating System :: OS Independent
Classifier: Programming Language :: Python
Classifier: Topic :: Software Development :: Libraries :: Python Modules
Classifier: Topic :: Communications :: Chat :: Internet Relay Chat
Requires-Dist: helga
